c2i_athena_mcp/README.md
c2i_athena_mcp/__init__.py
c2i_athena_mcp/athena_client.py
c2i_athena_mcp/cli.py
c2i_athena_mcp/examples.py
c2i_athena_mcp/mrd_calculation_tools.py
c2i_athena_mcp/server.py
c2i_athena_mcp/helpers/__init__.py
c2i_athena_mcp/helpers/files.py
c2i_athena_mcp/helpers/prompts.py
c2i_athena_mcp/instructions/mrd_detection_rate_calculation.md
c2i_athena_mcp/instructions/prompts.md
c2i_athena_mcp/instructions/data_lake/data_lake_query_examples.md
c2i_athena_mcp/instructions/data_lake/data_lake_schema.md
c2i_athena_mcp-1.0.3.dist-info/METADATA
c2i_athena_mcp-1.0.3.dist-info/WHEEL
c2i_athena_mcp-1.0.3.dist-info/entry_points.txt
c2i_athena_mcp-1.0.3.dist-info/RECORD
