Metadata-Version: 2.4
Name: c2i-athena-mcp
Version: 1.0.3
Summary: C2i Genomics Athena MCP Server with MRD calculation tools
Project-URL: Homepage, https://github.com/c2i-genomics/c2i-athena-mcp
Project-URL: Documentation, https://github.com/c2i-genomics/c2i-athena-mcp#readme
Project-URL: Repository, https://github.com/c2i-genomics/c2i-athena-mcp
Project-URL: Issues, https://github.com/c2i-genomics/c2i-athena-mcp/issues
Author-email: C2i Genomics <dev@c2i-genomics.com>
License: MIT
Keywords: athena,aws,genomics,mcp,mrd
Classifier: Development Status :: 4 - Beta
Classifier: Intended Audience :: Science/Research
Classifier: License :: OSI Approved :: MIT License
Classifier: Programming Language :: Python :: 3
Classifier: Programming Language :: Python :: 3.11
Classifier: Programming Language :: Python :: 3.12
Classifier: Topic :: Scientific/Engineering :: Bio-Informatics
Requires-Python: >=3.11
Requires-Dist: boto3>=1.34.0
Requires-Dist: fastmcp>=0.3.0
Requires-Dist: mcp>=1.0.0
Requires-Dist: numpy>=1.24.0
Requires-Dist: pandas>=2.0.0
Requires-Dist: pydantic>=2.0.0
Requires-Dist: python-dotenv>=1.0.0
Provides-Extra: dev
Requires-Dist: black>=23.0.0; extra == 'dev'
Requires-Dist: pytest-asyncio>=0.21.0; extra == 'dev'
Requires-Dist: pytest>=7.0; extra == 'dev'
Requires-Dist: ruff>=0.1.0; extra == 'dev'
